LICENSE.txt
MANIFEST.in
README.rst
setup.py
PyRhO.egg-info/PKG-INFO
PyRhO.egg-info/SOURCES.txt
PyRhO.egg-info/dependency_links.txt
PyRhO.egg-info/requires.txt
PyRhO.egg-info/top_level.txt
notebooks/PyRhO_Demo.ipynb
pyrho/IPythonGUI.py
pyrho/__init__.py
pyrho/config.py
pyrho/fitting.py
pyrho/loadData.py
pyrho/models.py
pyrho/parameters.py
pyrho/protocols.py
pyrho/simulators.py
pyrho/utilities.py
pyrho/NEURON/RhO3.mod
pyrho/NEURON/RhO3c.mod
pyrho/NEURON/RhO4.mod
pyrho/NEURON/RhO4c.mod
pyrho/NEURON/RhO6.mod
pyrho/NEURON/RhO6c.mod
pyrho/NEURON/__init__.py
pyrho/NEURON/install_neuron.sh
pyrho/NEURON/minimal.hoc
pyrho/NEURON/minimal.py
pyrho/NEURON/oocyte.hoc
pyrho/datasets/ChR2.pkl
pyrho/datasets/__init__.py
pyrho/gui/3state_model.png
pyrho/gui/4state_model.png
pyrho/gui/6state_model.png
pyrho/gui/PyRhO_logo.png
pyrho/gui/__init__.py
pyrho/gui/chirp6s.png
pyrho/gui/custom6s.png
pyrho/gui/delta6s.png
pyrho/gui/ramp6s.png
pyrho/gui/recovery6s.png
pyrho/gui/rectifier6s.png
pyrho/gui/shortPulse6s.png
pyrho/gui/sinusoid6s.png
pyrho/gui/step6s.png