Metadata-Version: 1.1
Name: PyRhO
Version: 0.9.4
Summary: Fit and characterise rhodopsin photocurrents
Home-page: https://github.com/ProjectPyRhO/PyRhO/
Author: Benjamin D. Evans
Author-email: ben.d.evans@gmail.com
License: BSD
Keywords: optogenetics rhodopsin opsin brain neuroscience neuron brian jupyter
Platform: Linux
Platform: Mac OS X
Platform: Windows
Classifier: Development Status :: 4 - Beta
Classifier: Intended Audience :: Science/Research
Classifier: Intended Audience :: Education
Classifier: Topic :: Scientific/Engineering
Classifier: Topic :: Scientific/Engineering :: Medical Science Apps.
Classifier: Topic :: Scientific/Engineering :: Bio-Informatics
Classifier: Topic :: Scientific/Engineering :: Artificial Life
Classifier: Topic :: Scientific/Engineering :: Human Machine Interfaces
Classifier: License :: OSI Approved :: BSD License
Classifier: Programming Language :: Python
Classifier: Programming Language :: Python :: 3
Classifier: Programming Language :: Python :: 3.1
Classifier: Programming Language :: Python :: 3.2
Classifier: Programming Language :: Python :: 3.3
Classifier: Programming Language :: Python :: 3.4
Classifier: Framework :: IPython
Classifier: Natural Language :: English
Classifier: Operating System :: OS Independent
